cloudsigma/__init__.py
cloudsigma/bulk.py
cloudsigma/conf.py
cloudsigma/errors.py
cloudsigma/generic.py
cloudsigma/metadata.py
cloudsigma/resource.py
cloudsigma/resumable_upload.py
cloudsigma/scenarios.py
cloudsigma/upload_client.py
cloudsigma/version.py
cloudsigma-2.0.0.dist-info/LICENSE
cloudsigma-2.0.0.dist-info/METADATA
cloudsigma-2.0.0.dist-info/WHEEL
cloudsigma-2.0.0.dist-info/top_level.txt
cloudsigma-2.0.0.dist-info/RECORD
